---
title: 单例模式
created: 2022-05-30 23:10:02
updated: 2022-05-31 15:36:59
tags: 
- #atom
---
# 单例模式

## 线程安全的实现

### 懒汉式：
[[2_0_2-计算机科学/2_0_2_1_2_1-软件方法学/设计模式/Balking|balking]]模式：

```java
public final class Singleton {
    private Singleton() {
    }
 
    private static Singleton INSTANCE = null;
 
    public static synchronized Singleton getInstance() {
        if (INSTANCE == null) {
	        INSTANCE = new Singleton();
        }
        return INSTANCE;
    }
}
```

### 双重校验锁

>由懒汉模式改进

#### 存在问题版

可以发现上面的实现除了第一次和第二次必须要锁，后续只要简单判断标志位即可，所以外面多加一层判断标志，防止后续不必要的锁操作：

```java
public final class Singleton {
    private Singleton() {
    }
 
    private static Singleton INSTANCE = null;
 
    public static Singleton getInstance() {
	    // 首次访问会[[2_0_2-计算机科学/2_0_2_1_2_3-软件系统/2_0_2_1_2_3_1-操作系统/同步|同步]]，但之后的访问就没有synchronized
        if(INSTANCE == null) {
	        synchronized(Singleton.class) {
		        if (INSTANCE == null) {
		            INSTANCE = new Singleton();
		        }
	        }
        }
        return INSTANCE;
    }
}
```

>理解上来说，最外层的判断才是后加的，双重校验锁是由懒汉模式进化而来。

##### 问题分析

对应jvm字节码：
```java
0: getstatic     #2                  // Field INSTANCE:Lcn/itcast/n5/Singleton;
3: ifnonnull     37
6: ldc           #3                  // class cn/itcast/n5/Singleton
8: dup
9: astore_0
10: monitorenter
11: getstatic     #2                  // Field INSTANCE:Lcn/itcast/n5/Singleton;
14: ifnonnull     27
17: new           #3                  // class cn/itcast/n5/Singleton
20: dup
21: invokespecial #4                  // Method "<init>":()V
24: putstatic     #2                  // Field INSTANCE:Lcn/itcast/n5/Singleton;
27: aload_0
28: monitorexit
29: goto          37
32: astore_1
33: aload_0
34: monitorexit
35: aload_1
36: athrow
37: getstatic     #2                  // Field INSTANCE:Lcn/itcast/n5/Singleton;
40: areturn
```

- 17 表示创建对象，将对象引用入栈  // new Singleton
- 20 表示复制一份对象引用  // 引用地址
- 21 表示利用一个对象引用，调用构造方法 
- 24 表示利用一个对象引用，赋值给 static INSTANCE
也许 jvm 会优化为：先执行 24，再执行 21。如果两个线程 t1，t2 按如下时间序列执行：
![[z-oblib/z2-attachments/Pasted image 20220531152646.png]]


外层if在[[2_0_2-计算机科学/2_0_2_1_2_0-软件语言/Java/2-并发编程/synchronized|synchronized]]之外，不受保护，并且对象可能先产生地址再被初始化，导致外层if可能读到未初始化的对象：

关键在于 0: getstatic 这行代码在 monitor 控制之外，它就像之前举例中不守规则的人，可以越过 [[2_0_2-计算机科学/2_0_2_1_2_0-软件语言/Java/2-并发编程/monitor|monitor]] 读取INSTANCE 变量的值。
这时 t1 还未完全将构造方法执行完毕，如果在构造方法中要执行很多初始化操作，那么 t2 拿到的是将是一个未初始化完毕的单例。
对 INSTANCE 使用 volatile 修饰即可，可以禁用指令重排，但要注意在 JDK 5 以上的版本的 [[2_0_2-计算机科学/2_0_2_1_2_0-软件语言/Java/1-高级特性/volatile|volatile]] 才会真正有效。

#### 改进版

通过volatile保证[[2_0_2-计算机科学/2_0_2_1_2_0-软件语言/Java/2-并发编程/可见性|可见性]]和[[2_0_2-计算机科学/2_0_2_1_2_0-软件语言/Java/2-并发编程/有序性|有序性]]。

```java
public final class Singleton {
    private Singleton() { }
    private static volatile Singleton INSTANCE = null;
    public static Singleton getInstance() {
        // 实例没创建，才会进入内部的 synchronized代码块
        if (INSTANCE == null) {            
            synchronized (Singleton.class) { // t2
                // 也许有其它线程已经创建实例，所以再判断一次
                if (INSTANCE == null) { // t1
                    INSTANCE = new Singleton();
                }
            }
        }
        return INSTANCE;
    }
}
```

