---
title: 泛型
created: 2022-06-15 14:01:00
updated: 2022-06-15 17:30:45
tags: 
- #atom
---
# 泛型

## 类型擦除

下面的例子无法编译通过：

```java
// generics/HasF.java

public class HasF {
public void f() {
System.out.println("HasF.f()");
}
}
```

```java
// generics/Manipulation.java  
// {WillNotCompile}  
  
class Manipulator<T> {  
    private T obj;  
  
    Manipulator(T x) {  
        obj = x;  
    }  
  
    // Error: cannot find symbol: method f():  
    // 传入时类型就擦除了，obj现在时Object类型，没有f方法
    public void manipulate() {  
        obj.f();  
    }  
  
}  
  
public class Manipulation {  
    public static void main(String[] args) {  
        HasF hf = new HasF();  
        // 这里只做了传入的对象是否未HasF类型判断，之后就擦除了类型
        Manipulator<HasF> manipulator = new Manipulator<>(hf);  
        manipulator.manipulate();  
    }  
}
```

因为`Manipulator<HasF>`这里`<HasF>`的作用只是对等号右边传入的`new Manipulator<>(hf)`进行了类型检测，随后就将其类型擦除为Objcet。在`manipulate()`方法中编译器只知道obj对象是个Object类型，没有f()方法。

### 给定泛型边界

为了调用 f()，我们必须协助泛型类，给定 泛型类一个边界，以此告诉编译器只能接受遵循这个边界的类型。这里重用了 extends 关键字。由于有了边界，下面的代码就能通过编译：

```java
public class Manipulator2<T extends HasF> {  
    private T obj;  
  
    Manipulator2(T x) {  
        obj = x;  
    }  
  
    public void manipulate() {  
        obj.f();  
    }  
  
}
```

边界 `<T extends HasF>` 声明 T 必须是 HasF 类型或其子类。如果情况确实如此， 就可以安全地在 obj 上调用 f() 方法。
**泛型类型参数会擦除到它的第一个边界**（可能有多个边界，稍后你将看到）。
java还提到了类型参数的擦除。编译器实际上会把类型参数替换为它的擦除边界，就像上面 的示例，T 擦除到了 HasF，就像在类的声明中用 HasF 替换了 T 一样。

> 例如，`List<T>` 这样的类型注解会被 擦除为 List，普通的类型变量在未指定边界的情况下会被擦除为 Object。

```java
// generics/Manipulator3.java  
  
class Manipulator3 {  
    private HasF obj;  
  
    Manipulator3(HasF x) {  
        obj = x;  
    }  
  
    public void manipulate() {  
        obj.f();  
    }  
}
```

这提出了很重要的一点：泛型只有在类型参数比某个具体类型（以及其子类）更加
“泛化”——代码能跨多个类工作时才有用。因此，类型参数和它们在有用的泛型代码中
的应用，通常比简单的类替换更加复杂。但是，不能因此认为使用 `<T extends HasF>`
形式就是有缺陷的。例如，如果某个类有一个返回 T 的方法，那么泛型就有所帮助，因
为它们之后将返回确切的类型：

```java
// generics/ReturnGenericType.java  
  
public class ReturnGenericType<T extends HasF> {  
    private T obj;  
  
    ReturnGenericType(T x) {  
        obj = x;  
    }  
  
    public T get() {  
        return obj;  
    }  
  
}
```

### 代价

擦除的代价是显著的。泛型不能用于显式地引用运行时类型的操作中，例如转型、 instanceof 操作和 new 表达式。因为所有关于参数的类型信息都丢失了，当你在编写 泛型代码时，必须时刻提醒自己，你只是看起来拥有有关参数的类型信息而已。
考虑如下的代码段：

```java
class Foo<T> {  
    T var;  
}
```

```java
Foo<Cat> f = new Foo<>();
```

看上去当你创建一个 Foo 实例时：class Foo 中的代码应该知道现在工作于 Cat 之上。泛型语法也在强烈暗示整个类中所有 T 出现的地方都被替换，就像在 C++ 中一样。但是事实并非如此，当你在编写这个类的代码时，必须提醒自己："不，这只是一个 **Object**"。

### 时机

泛型的所有动作都发生在边 界处——对入参的编译器检查和对返回值的转型。这有助于澄清对擦除的困惑，记住： “边界就是动作发生的地方”。

对比泛型和非泛型的两段代码对应的字节码：

非泛型：
```java
// generics/SimpleHolder.java  
  
public class SimpleHolder {  
    private Object obj;  
  
    public void set(Object obj) {  
        this.obj = obj;  
    }  
  
    public Object get() {  
        return obj;  
    }  
  
    public static void main(String[] args) {  
        SimpleHolder holder = new SimpleHolder();  
        holder.set("Item");  
        // 需要手动类型转换
        String s = (String) holder.get();  
    }  
  
}
```

非泛型字节码：
```java
public void set(java.lang.Object);  
        0: aload_0  
        1: aload_1  
        2: putfield #2; // Field obj:Object;  
        5: return  
  
public java.lang.Object get();  
        0: aload_0  
        1: getfield #2; // Field obj:Object;  
        4: areturn  
  
public static void main(java.lang.String[]);  
        0: new #3; // class SimpleHolder  
        3: dup  
        4: invokespecial #4; // Method "<init>":()V  
        7: astore_1  
        8: aload_1  
        9: ldc #5; // String Item  
        11: invokevirtual #6; // Method set:(Object;)V  
        14: aload_1  
        15: invokevirtual #7; // Method get:()Object;  
        18: checkcast #8; // class java/lang/String  
        21: astore_2  
        22: return
```

泛型：

```java
// generics/GenericHolder2.java  
  
public class GenericHolder2<T> {  
    private T obj;  
  
    public void set(T obj) {  
        this.obj = obj;  
    }  
  
    public T get() {  
        return obj;  
    }  
  
    public static void main(String[] args) {  
        GenericHolder2<String> holder = new GenericHolder2<>();  
        holder.set("Item"); 
        // 使用了泛型，这里不用手动类型转换了 
        String s = holder.get();  
    }  
  
}
```

泛型字节码：
```java
public void set(java.lang.Object);  
        0: aload_0  
        1: aload_1  
        2: putfield #2; // Field obj:Object;  
        5: return  
  
public java.lang.Object get();  
        0: aload_0  
        1: getfield #2; // Field obj:Object;  
        4: areturn  
  
public static void main(java.lang.String[]);  
        0: new #3; // class GenericHolder2  
        3: dup  
        4: invokespecial #4; // Method "<init>":()V  
        7: astore_1  
        8: aload_1  
        9: ldc #5; // String Item  
        11: invokevirtual #6; // Method set:(Object;)V  
        14: aload_1  
        15: invokevirtual #7; // Method get:()Object;  
        18: checkcast #8; // class java/lang/String  
        21: astore_2  
        22: return
```

两个代码所产生的字节码是相同的。
对进入 set() 的类型进行检查是不需要的，因为这将由编译器执行。而对 get() 返回的值进行转型仍然是需要的，只不过不需要你来操作，它由**编译器自动插入**。
get() 和 set() 产生了相同的字节码，这就告诉我们泛型的所有动作都发生在边 界处——对入参的编译器检查和对返回值的转型。这有助于澄清对擦除的困惑，记住： “边界就是动作发生的地方”。

## 边界

由于擦除会删除类型信息，因此唯一可用于无限制泛型参数的方法是那些 Object 可用的方法。但是，如果将该参数限制为某类型的子集，则可以调用该子集中的方法。
为了应用约束，Java 泛型使用了 extends 关键字。

## 数组协变

在了解通配符之前，先来了解一下数组。Java 中的数组是[[2_0_2-计算机科学/2_0_2_1_2_0-软件语言/2_0_2_1_2_0_0-Java/2_0_2_1_2_0_0_1-高级特性/协变|协变]]的，什么意思？看下面的例子：

```java
class Fruit {}
class Apple extends Fruit {}
class Jonathan extends Apple {}
class Orange extends Fruit {}

public class CovariantArrays {
    public static void main(String[] args) {       
        Fruit[] fruit = new Apple[10];
        fruit[0] = new Apple(); // OK
        fruit[1] = new Jonathan(); // OK
        // Runtime type is Apple[], not Fruit[] or Orange[]:
        try {
            // Compiler allows you to add Fruit:
            fruit[0] = new Fruit(); // ArrayStoreException
        } catch(Exception e) { System.out.println(e); }
        try {
            // Compiler allows you to add Oranges:
            fruit[0] = new Orange(); // ArrayStoreException
        } catch(Exception e) { System.out.println(e); }
        }
} /* Output:
java.lang.ArrayStoreException: Fruit
java.lang.ArrayStoreException: Orange
*///:~
```

`main` 方法中的第一行，创建了一个 `Apple` 数组并把它赋给 `Fruit` 数组的引用。这是有意义的，`Apple` 是 `Fruit` 的子类，一个 `Apple` 对象也是一种 `Fruit` 对象，所以一个 `Apple` 数组也是一种 `Fruit` 的数组。这称作**数组的协变**，Java 把数组设计为协变的，对此是有争议的，有人认为这是一种缺陷。

尽管 `Apple[]` 可以 “向上转型” 为 `Fruit[]`，但数组元素的实际类型还是 `Apple`，我们只能向数组中放入 `Apple`或者 `Apple` 的子类。在上面的代码中，向数组中放入了 `Fruit` 对象和 `Orange` 对象。对于编译器来说，这是可以通过编译的，但是在运行时期，JVM 能够知道数组的实际类型是 `Apple[]`，所以当其它对象加入数组的时候就会抛出异常。

泛型设计的目的之一是要使这种运行时期的错误在编译期就能发现，看看用泛型容器类来代替数组会发生什么：

```java
// Compile Error: incompatible types:
ArrayList<Fruit> flist = new ArrayList<Apple>();

```

上面的代码根本就无法编译。当涉及到泛型时， 尽管 `Apple` 是 `Fruit` 的子类型，但是 `ArrayList<Apple>` 不是 `ArrayList<Fruit>` 的子类型，泛型不支持协变。

## 通配符

从上面我们知道，`List<Number> list = ArrayList<Integer>` 这样的语句是无法通过编译的，尽管 `Integer` 是 `Number` 的子类型。那么如果我们确实需要建立这种 “向上转型” 的关系怎么办呢？这就需要通配符来发挥作用了。

### 上边界

> 所有对象都当作是T
> 主要是用来处理泛型方法的返回值，返回的东西当作是T类型对待

利用 `<? extends Fruit>` 形式的通配符，可以实现泛型的向上转型：

```java
public class GenericsAndCovariance {
    public static void main(String[] args) {
        // Wildcards allow covariance:
        List<? extends Fruit> flist = new ArrayList<Apple>();
        // Compile Error: can’t add any type of object:
        // flist.add(new Apple());
        // flist.add(new Fruit());
        // flist.add(new Object());
        flist.add(null); // Legal but uninteresting
        // We know that it returns at least Fruit:
        Fruit f = flist.get(0);
    }
}
```

`flist` 的类型可以看作是List<某个继承了Fruit的类型>。
注意不是指这个list里可以**同时**放不同的Fruit子类，而是指flist可以指向指定边界内的List<>对象。

无法传递对象了：加了界限，但又不完全确定到底是哪个具体类，导致无法向其中添加任意元素，甚至Object都不可以，只能添加null。

### 下边界

> 所有对象起码是个T
> 主要是处理向泛型方法传递参数，所有传入的对象起码是个T，或者是T的子类。

> 超类型通配符。
> 逆变。

通配符的另一个方向是　“超类型的通配符“: `? super T`，`T` 是类型参数的下界。使用这种形式的通配符，我们就可以 ”传递对象” 了。还是用例子解释：
```java
public class SuperTypeWildcards {
    static void writeTo(List<? super Apple> apples) {
        apples.add(new Apple());
        apples.add(new Jonathan());
        // apples.add(new Fruit()); // Error
    }
}
```

`writeTo` 方法的参数 `apples` 的类型是 `List<? super Apple>`，它表示某种类型的 List，我们不知道实际类型是什么，但是这个类型肯定是 `Apple` 的父类型。因此，我们可以知道向这个 List 添加一个 `Apple` 或者其子类型的对象是安全的，这些对象都可以**向上**转型为 `Apple`。但是我们不知道加入 `Fruit` 对象是否安全，因为那样会使得这个 List 添加跟 `Apple` 无关的类型。

### 利用上下边界面向泛型类型进行读取和写入

如何向泛型类型中 “写入” ( 传递对象给方法参数) 以及如何从泛型类型中 “读取” ( 从方法中返回对象 )。下面是一个例子：

```java
public class Collections { 
  public static <T> void copy(List<? super T> dest, List<? extends T> src) 
  {
      for (int i=0; i<src.size(); i++) 
        dest.set(i,src.get(i)); 
  } 
}
```

`src` 是原始数据的 List，因为要从这里面读取数据，所以用了上边界限定通配符：`<? extends T>`，取出的元素转型为 `T`。`dest` 是要写入的目标 List，所以用了下边界限定通配符：`<? super T>`，可以写入的元素类型是 `T` 及其子类型。

### 无边界

还有一种通配符是无边界通配符，它的使用形式是一个单独的问号：`List<?>`，也就是没有任何限定。不做任何限制，和`<? extends Object>`效果一样。

跟不用类型参数的 `List` 有什么区别呢？
`List<?> list` 表示 `list` 是持有某种特定类型的 List，但是不知道具体是哪种类型。那么我们可以向其中添加对象吗？当然**不可以**，因为并不知道实际是哪种类型，所以不能添加任何类型，这是不安全的。
而单独的 `List list` ，也就是没有传入泛型参数，表示这个 list 持有的元素的类型是 `Object`，因此**可以**添加任何类型的对象，只不过编译器会有警告信息。

> List`<?>`里面的元素，如果你取出来，会都被转化为Object。
> 加了`<?>`那么会把返回值自动转换为Object。
> 不加则需要自己手动转换。

## 总结

通配符的使用可以对泛型参数做出某些限制，使代码更安全，对于上边界和下边界限定的通配符总结如下：

- 使用 `List<? extends C> list` 这种形式，表示 list 可以引用一个 `ArrayList` ( 或者其它 List 的 子类 ) 的对象，这个对象包含的元素类型是 `C` 的子类型 ( 包含 `C` 本身）的一种。
- 使用 `List<? super C> list` 这种形式，表示 list 可以引用一个 `ArrayList` ( 或者其它 List 的 子类 ) 的对象，这个对象包含的元素就类型是 `C` 的超类型 ( 包含 `C` 本身 ) 的一种。